word_unscrambler/__init__.py
word_unscrambler-0.1.2.dist-info/METADATA
word_unscrambler-0.1.2.dist-info/WHEEL
word_unscrambler-0.1.2.dist-info/licenses/LICENSE
word_unscrambler-0.1.2.dist-info/RECORD
