Metadata-Version: 2.1
Name: word_unscrambler
Version: 0.1.2
Summary: A python module that unscrambles characters into words
Project-URL: Homepage, https://github.com/rufus-gh/word-unscrambler/
Project-URL: Issues, https://github.com/rufus-gh/word-unscrambler/issues
Author-email: Rufus Gordon-Heywood <rufus.gordonheywood@education.nsw.gov.au>
License-File: LICENSE
Classifier: License :: OSI Approved :: MIT License
Classifier: Operating System :: OS Independent
Classifier: Programming Language :: Python :: 3
Requires-Python: >=3.5
